sol_div/__init__.py
sol_div/div.py
sol_div-0.1.0.dist-info/METADATA
sol_div-0.1.0.dist-info/WHEEL
sol_div-0.1.0.dist-info/top_level.txt
sol_div-0.1.0.dist-info/RECORD
